setup.py
zdfm.py
zdfm.egg-info/PKG-INFO
zdfm.egg-info/SOURCES.txt
zdfm.egg-info/dependency_links.txt
zdfm.egg-info/entry_points.txt
zdfm.egg-info/top_level.txt