Metadata-Version: 1.0
Name: zdfm
Version: 0.8
Summary: Downloader for the ZDF Mediathek. Python 3 required.
Home-page: http://github.com/enkore/zdfm/
Author: Marian Beermann
Author-email: public@enkore.de
License: MIT
Platform: UNKNOWN
